opentmi_client/__init__.py
opentmi_client/api/__init__.py
opentmi_client/api/client.py
opentmi_client/api/build/Build.py
opentmi_client/api/build/Ci.py
opentmi_client/api/build/Hardware.py
opentmi_client/api/build/Target.py
opentmi_client/api/build/Vcs.py
opentmi_client/api/build/__init__.py
opentmi_client/api/event/Event.py
opentmi_client/api/event/Priority.py
opentmi_client/api/event/Ref.py
opentmi_client/api/event/__init__.py
opentmi_client/api/resource/Hardware.py
opentmi_client/api/resource/Item.py
opentmi_client/api/resource/Resource.py
opentmi_client/api/resource/Status.py
opentmi_client/api/resource/__init__.py
opentmi_client/api/result/Dut.py
opentmi_client/api/result/Environment.py
opentmi_client/api/result/Execution.py
opentmi_client/api/result/File.py
opentmi_client/api/result/Framework.py
opentmi_client/api/result/Job.py
opentmi_client/api/result/Provider.py
opentmi_client/api/result/Result.py
opentmi_client/api/result/Sut.py
opentmi_client/api/result/__init__.py
opentmi_client/api/testcase/Compatible.py
opentmi_client/api/testcase/Execution.py
opentmi_client/api/testcase/OtherInfo.py
opentmi_client/api/testcase/Skip.py
opentmi_client/api/testcase/Status.py
opentmi_client/api/testcase/Testcase.py
opentmi_client/api/testcase/Verification.py
opentmi_client/api/testcase/__init__.py
opentmi_client/cli/__init__.py
opentmi_client/cli/main.py
opentmi_client/transport/HttpAdapter.py
opentmi_client/transport/__init__.py
opentmi_client/transport/transport.py
opentmi_client/utils/Base.py
opentmi_client/utils/Query.py
opentmi_client/utils/__init__.py
opentmi_client/utils/decorators.py
opentmi_client/utils/exceptions.py
opentmi_client/utils/tools.py
opentmi_client-0.12.0.dist-info/LICENSE
opentmi_client-0.12.0.dist-info/METADATA
opentmi_client-0.12.0.dist-info/WHEEL
opentmi_client-0.12.0.dist-info/entry_points.txt
opentmi_client-0.12.0.dist-info/top_level.txt
opentmi_client-0.12.0.dist-info/RECORD
