Metadata-Version: 2.1
Name: opentmi-client
Version: 0.12.0
Summary: opentmi-client
Home-page: https://github.com/OpenTMI/opentmi-pyclient.git
Author: Jussi Vatjus-Anttila
Author-email: jussiva@gmail.com
Maintainer: Jussi Vatjus-Anttila
Maintainer-email: jussiva@gmail.com
License: MIT
Keywords: opentmi ci cd api sdk
Classifier: Programming Language :: Python :: 3.8
Classifier: Programming Language :: Python :: 3.9
Classifier: Programming Language :: Python :: 3.10
Classifier: Programming Language :: Python :: 3.11
Classifier: Programming Language :: Python :: 3.12
Classifier: License :: OSI Approved :: MIT License
Classifier: Operating System :: OS Independent
License-File: LICENSE
Requires-Dist: requests>=2.13.0
Requires-Dist: urllib3<3,>=1.26.0
Requires-Dist: jsonmerge
Requires-Dist: six
Requires-Dist: pydash
Requires-Dist: junitparser<2.0.0
